Lab002/src/ALU.v
`timescale 1ns / 1ps
// ============================================================
// Lab02 - ALU de 4 bits (logica puramente combinacional)
//
//   OP | Operacion
//   00 | A + B   (suma, sin acarreo: resultado modulo 16)
//   01 | A - B   (resta, complemento a 2: 3 - 5 = 1110)
//   10 | A & B   (AND bit a bit)
//   11 | A | B   (OR bit a bit)
//
// No tiene reloj ni registros: la salida depende solo de las
// entradas actuales. Todos los casos del case asignan OUTT,
// por lo que no se infieren latches.
// ============================================================
module ALU (
    input      [3:0] A,
    input      [3:0] B,
    input      [1:0] OP,
    output reg [3:0] OUTT
);

    localparam [1:0] SUM_OP = 2'b00;
    localparam [1:0] RES_OP = 2'b01;
    localparam [1:0] AND_OP = 2'b10;
    localparam [1:0] OR_OP  = 2'b11;

    always @(*) begin
        case (OP)
            SUM_OP:  OUTT = A + B;
            RES_OP:  OUTT = A - B;
            AND_OP:  OUTT = A & B;
            OR_OP:   OUTT = A | B;
            default: OUTT = 4'b0000;
        endcase
    end

endmodule

Lab002/sim/tb_alu.v
`timescale 1ns / 1ps
// ============================================================
// Testbench autoverificable de la ALU (Lab02 - Ejercicio 2)
//  - Recorre las 4 operaciones con las 256 combinaciones de A y B
//  - Compara OUTT con un modelo de referencia
//  - Cambia OP con A y B fijos para ver la respuesta combinacional
// ============================================================
module tb_alu;

    reg  [3:0] A  = 4'd0;
    reg  [3:0] B  = 4'd0;
    reg  [1:0] OP = 2'b00;
    wire [3:0] OUTT;

    reg  [3:0] esperado;
    integer    op_i, a_i, b_i;
    integer    errores = 0;
    integer    pruebas = 0;

    ALU dut (
        .A    (A),
        .B    (B),
        .OP   (OP),
        .OUTT (OUTT)
    );

    // Modelo de referencia
    always @(*) begin
        case (OP)
            2'b00: esperado = A + B;
            2'b01: esperado = A - B;
            2'b10: esperado = A & B;
            2'b11: esperado = A | B;
        endcase
    end

    task revisar;
        begin
            pruebas = pruebas + 1;
            if (OUTT !== esperado) begin
                $display("ERROR: OP=%b A=%0d B=%0d -> OUTT=%0d, esperado %0d",
                         OP, A, B, OUTT, esperado);
                errores = errores + 1;
            end
        end
    endtask

    initial begin
        $dumpfile("tb_alu.vcd");
        $dumpvars(0, tb_alu);

        //------------------------------------------------
        // Parte 1: casos representativos (para ver en GTKWave)
        // A y B fijos, se cambia solo OP
        //------------------------------------------------
        A = 4'd5; B = 4'd3;
        for (op_i = 0; op_i < 4; op_i = op_i + 1) begin
            OP = op_i; #10; revisar;
            $display("A=%0d B=%0d OP=%b -> OUTT=%b (%0d)", A, B, OP, OUTT, OUTT);
        end

        A = 4'd3; B = 4'd5;          // resta negativa: 3 - 5 = -2 -> 1110
        for (op_i = 0; op_i < 4; op_i = op_i + 1) begin
            OP = op_i; #10; revisar;
            $display("A=%0d B=%0d OP=%b -> OUTT=%b (%0d)", A, B, OP, OUTT, OUTT);
        end

        A = 4'd15; B = 4'd1;         // desbordamiento en la suma: 15 + 1 = 0
        for (op_i = 0; op_i < 4; op_i = op_i + 1) begin
            OP = op_i; #10; revisar;
            $display("A=%0d B=%0d OP=%b -> OUTT=%b (%0d)", A, B, OP, OUTT, OUTT);
        end

        //------------------------------------------------
        // Parte 2: prueba exhaustiva (4 x 16 x 16 = 1024 casos)
        //------------------------------------------------
        for (op_i = 0; op_i < 4; op_i = op_i + 1)
            for (a_i = 0; a_i < 16; a_i = a_i + 1)
                for (b_i = 0; b_i < 16; b_i = b_i + 1) begin
                    OP = op_i; A = a_i; B = b_i;
                    #1; revisar;
                end

        $display("--------------------------------------------");
        if (errores == 0) $display("ALU: PASO - %0d casos verificados", pruebas);
        else              $display("ALU: FALLO - %0d errores en %0d casos", errores, pruebas);
        $display("--------------------------------------------");
        $finish;
    end

endmodule

Lab002/sim/tb_alu.vcd
$date
	Mon Sep 28 21:53:14 2026
$end
$version
	Icarus Verilog
$end
$timescale
	1ps
$end
$scope module tb_alu $end
$var wire 4 ! OUTT [3:0] $end
$var reg 4 " A [3:0] $end
$var reg 4 # B [3:0] $end
$var reg 2 $ OP [1:0] $end
$var reg 4 % esperado [3:0] $end
$var integer 32 & a_i [31:0] $end
$var integer 32 ' b_i [31:0] $end
$var integer 32 ( errores [31:0] $end
$var integer 32 ) op_i [31:0] $end
$var integer 32 * pruebas [31:0] $end
$scope module dut $end
$var wire 4 + A [3:0] $end
$var wire 4 , B [3:0] $end
$var wire 2 - OP [1:0] $end
$var parameter 2 . AND_OP $end
$var parameter 2 / OR_OP $end
$var parameter 2 0 RES_OP $end
$var parameter 2 1 SUM_OP $end
$var reg 4 2 OUTT [3:0] $end
$upscope $end
$scope task revisar $end
$upscope $end
$upscope $end
$enddefinitions $end
$comment Show the parameter values. $end
$dumpall
b0 1
b1 0
b11 /
b10 .
$end
#0
$dumpvars
b1000 2
b0 -
b11 ,
b101 +
b0 *
b0 )
b0 (
bx '
bx &
b1000 %
b0 $
b11 #
b101 "
b1000 !
$end
#10000
b10 !
b10 2
b10 %
b1 $
b1 -
b1 )
b1 *
#20000
b1 %
b1 !
b1 2
b10 $
b10 -
b10 )
b10 *
#30000
b111 !
b111 2
b111 %
b11 $
b11 -
b11 )
b11 *
#40000
b1000 %
b1000 !
b1000 2
b0 $
b0 -
b101 #
b101 ,
b11 "
b11 +
b0 )
b100 *
#50000
b1110 !
b1110 2
b1110 %
b1 $
b1 -
b1 )
b101 *
#60000
b1 %
b1 !
b1 2
b10 $
b10 -
b10 )
b110 *
#70000
b111 !
b111 2
b111 %
b11 $
b11 -
b11 )
b111 *
#80000
b0 %
b0 !
b0 2
b0 $
b0 -
b1 #
b1 ,
b1111 "
b1111 +
b0 )
b1000 *
#90000
b1110 !
b1110 2
b1110 %
b1 $
b1 -
b1 )
b1001 *
#100000
b1 %
b1 !
b1 2
b10 $
b10 -
b10 )
b1010 *
#110000
b1111 !
b1111 2
b1111 %
b11 $
b11 -
b11 )
b1011 *
#120000
b0 %
b0 !
b0 2
b0 #
b0 ,
b0 "
b0 +
b0 $
b0 -
b0 '
b0 &
b0 )
b1100 *
#121000
b1 !
b1 2
b1 %
b1 #
b1 ,
b1 '
b1101 *
#122000
b10 %
b10 !
b10 2
b10 #
b10 ,
b10 '
b1110 *
#123000
b11 !
b11 2
b11 %
b11 #
b11 ,
b11 '
b1111 *
#124000
b100 %
b100 !
b100 2
b100 #
b100 ,
b100 '
b10000 *
#125000
b101 !
b101 2
b101 %
b101 #
b101 ,
b101 '
b10001 *
#126000
b110 %
b110 !
b110 2
b110 #
b110 ,
b110 '
b10010 *
#127000
b111 !
b111 2
b111 %
b111 #
b111 ,
b111 '
b10011 *
#128000
b1000 %
b1000 !
b1000 2
b1000 #
b1000 ,
b1000 '
b10100 *
#129000
b1001 !
b1001 2
b1001 %
b1001 #
b1001 ,
b1001 '
b10101 *
#130000
b1010 %
b1010 !
b1010 2
b1010 #
b1010 ,
b1010 '
b10110 *
#131000
b1011 !
b1011 2
b1011 %
b1011 #
b1011 ,
b1011 '
b10111 *
#132000
b1100 %
b1100 !
b1100 2
b1100 #
b1100 ,
b1100 '
b11000 *
#133000
b1101 !
b1101 2
b1101 %
b1101 #
b1101 ,
b1101 '
b11001 *
#134000
b1110 %
b1110 !
b1110 2
b1110 #
b1110 ,
b1110 '
b11010 *
#135000
b1111 !
b1111 2
b1111 %
b1111 #
b1111 ,
b1111 '
b11011 *
#136000
b1 %
b1 !
b1 2
b0 #
b0 ,
b1 "
b1 +
b1 &
b0 '
b11100 *
#137000
b10 !
b10 2
b10 %
b1 #
b1 ,
b1 '
b11101 *
#138000
b11 %
b11 !
b11 2
b10 #
b10 ,
b10 '
b11110 *
#139000
b100 !
b100 2
b100 %
b11 #
b11 ,
b11 '
b11111 *
#140000
b101 %
b101 !
b101 2
b100 #
b100 ,
b100 '
b100000 *
#141000
b110 !
b110 2
b110 %
b101 #
b101 ,
b101 '
b100001 *
#142000
b111 %
b111 !
b111 2
b110 #
b110 ,
b110 '
b100010 *
#143000
b1000 !
b1000 2
b1000 %
b111 #
b111 ,
b111 '
b100011 *
#144000
b1001 %
b1001 !
b1001 2
b1000 #
b1000 ,
b1000 '
b100100 *
#145000
b1010 !
b1010 2
b1010 %
b1001 #
b1001 ,
b1001 '
b100101 *
#146000
b1011 %
b1011 !
b1011 2
b1010 #
b1010 ,
b1010 '
b100110 *
#147000
b1100 !
b1100 2
b1100 %
b1011 #
b1011 ,
b1011 '
b100111 *
#148000
b1101 %
b1101 !
b1101 2
b1100 #
b1100 ,
b1100 '
b101000 *
#149000
b1110 !
b1110 2
b1110 %
b1101 #
b1101 ,
b1101 '
b101001 *
#150000
b1111 %
b1111 !
b1111 2
b1110 #
b1110 ,
b1110 '
b101010 *
#151000
b0 !
b0 2
b0 %
b1111 #
b1111 ,
b1111 '
b101011 *
#152000
b10 %
b10 !
b10 2
b0 #
b0 ,
b10 "
b10 +
b10 &
b0 '
b101100 *
#153000
b11 !
b11 2
b11 %
b1 #
b1 ,
b1 '
b101101 *
#154000
b100 %
b100 !
b100 2
b10 #
b10 ,
b10 '
b101110 *
#155000
b101 !
b101 2
b101 %
b11 #
b11 ,
b11 '
b101111 *
#156000
b110 %
b110 !
b110 2
b100 #
b100 ,
b100 '
b110000 *
#157000
b111 !
b111 2
b111 %
b101 #
b101 ,
b101 '
b110001 *
#158000
b1000 %
b1000 !
b1000 2
b110 #
b110 ,
b110 '
b110010 *
#159000
b1001 !
b1001 2
b1001 %
b111 #
b111 ,
b111 '
b110011 *
#160000
b1010 %
b1010 !
b1010 2
b1000 #
b1000 ,
b1000 '
b110100 *
#161000
b1011 !
b1011 2
b1011 %
b1001 #
b1001 ,
b1001 '
b110101 *
#162000
b1100 %
b1100 !
b1100 2
b1010 #
b1010 ,
b1010 '
b110110 *
#163000
b1101 !
b1101 2
b1101 %
b1011 #
b1011 ,
b1011 '
b110111 *
#164000
b1110 %
b1110 !
b1110 2
b1100 #
b1100 ,
b1100 '
b111000 *
#165000
b1111 !
b1111 2
b1111 %
b1101 #
b1101 ,
b1101 '
b111001 *
#166000
b0 %
b0 !
b0 2
b1110 #
b1110 ,
b1110 '
b111010 *
#167000
b1 !
b1 2
b1 %
b1111 #
b1111 ,
b1111 '
b111011 *
#168000
b11 %
b11 !
b11 2
b0 #
b0 ,
b11 "
b11 +
b11 &
b0 '
b111100 *
#169000
b100 !
b100 2
b100 %
b1 #
b1 ,
b1 '
b111101 *
#170000
b101 %
b101 !
b101 2
b10 #
b10 ,
b10 '
b111110 *
#171000
b110 !
b110 2
b110 %
b11 #
b11 ,
b11 '
b111111 *
#172000
b111 %
b111 !
b111 2
b100 #
b100 ,
b100 '
b1000000 *
#173000
b1000 !
b1000 2
b1000 %
b101 #
b101 ,
b101 '
b1000001 *
#174000
b1001 %
b1001 !
b1001 2
b110 #
b110 ,
b110 '
b1000010 *
#175000
b1010 !
b1010 2
b1010 %
b111 #
b111 ,
b111 '
b1000011 *
#176000
b1011 %
b1011 !
b1011 2
b1000 #
b1000 ,
b1000 '
b1000100 *
#177000
b1100 !
b1100 2
b1100 %
b1001 #
b1001 ,
b1001 '
b1000101 *
#178000
b1101 %
b1101 !
b1101 2
b1010 #
b1010 ,
b1010 '
b1000110 *
#179000
b1110 !
b1110 2
b1110 %
b1011 #
b1011 ,
b1011 '
b1000111 *
#180000
b1111 %
b1111 !
b1111 2
b1100 #
b1100 ,
b1100 '
b1001000 *
#181000
b0 !
b0 2
b0 %
b1101 #
b1101 ,
b1101 '
b1001001 *
#182000
b1 %
b1 !
b1 2
b1110 #
b1110 ,
b1110 '
b1001010 *
#183000
b10 !
b10 2
b10 %
b1111 #
b1111 ,
b1111 '
b1001011 *
#184000
b100 %
b100 !
b100 2
b0 #
b0 ,
b100 "
b100 +
b100 &
b0 '
b1001100 *
#185000
b101 !
b101 2
b101 %
b1 #
b1 ,
b1 '
b1001101 *
#186000
b110 %
b110 !
b110 2
b10 #
b10 ,
b10 '
b1001110 *
#187000
b111 !
b111 2
b111 %
b11 #
b11 ,
b11 '
b1001111 *
#188000
b1000 %
b1000 !
b1000 2
b100 #
b100 ,
b100 '
b1010000 *
#189000
b1001 !
b1001 2
b1001 %
b101 #
b101 ,
b101 '
b1010001 *
#190000
b1010 %
b1010 !
b1010 2
b110 #
b110 ,
b110 '
b1010010 *
#191000
b1011 !
b1011 2
b1011 %
b111 #
b111 ,
b111 '
b1010011 *
#192000
b1100 %
b1100 !
b1100 2
b1000 #
b1000 ,
b1000 '
b1010100 *
#193000
b1101 !
b1101 2
b1101 %
b1001 #
b1001 ,
b1001 '
b1010101 *
#194000
b1110 %
b1110 !
b1110 2
b1010 #
b1010 ,
b1010 '
b1010110 *
#195000
b1111 !
b1111 2
b1111 %
b1011 #
b1011 ,
b1011 '
b1010111 *
#196000
b0 %
b0 !
b0 2
b1100 #
b1100 ,
b1100 '
b1011000 *
#197000
b1 !
b1 2
b1 %
b1101 #
b1101 ,
b1101 '
b1011001 *
#198000
b10 %
b10 !
b10 2
b1110 #
b1110 ,
b1110 '
b1011010 *
#199000
b11 !
b11 2
b11 %
b1111 #
b1111 ,
b1111 '
b1011011 *
#200000
b101 %
b101 !
b101 2
b0 #
b0 ,
b101 "
b101 +
b101 &
b0 '
b1011100 *
#201000
b110 !
b110 2
b110 %
b1 #
b1 ,
b1 '
b1011101 *
#202000
b111 %
b111 !
b111 2
b10 #
b10 ,
b10 '
b1011110 *
#203000
b1000 !
b1000 2
b1000 %
b11 #
b11 ,
b11 '
b1011111 *
#204000
b1001 %
b1001 !
b1001 2
b100 #
b100 ,
b100 '
b1100000 *
#205000
b1010 !
b1010 2
b1010 %
b101 #
b101 ,
b101 '
b1100001 *
#206000
b1011 %
b1011 !
b1011 2
b110 #
b110 ,
b110 '
b1100010 *
#207000
b1100 !
b1100 2
b1100 %
b111 #
b111 ,
b111 '
b1100011 *
#208000
b1101 %
b1101 !
b1101 2
b1000 #
b1000 ,
b1000 '
b1100100 *
#209000
b1110 !
b1110 2
b1110 %
b1001 #
b1001 ,
b1001 '
b1100101 *
#210000
b1111 %
b1111 !
b1111 2
b1010 #
b1010 ,
b1010 '
b1100110 *
#211000
b0 !
b0 2
b0 %
b1011 #
b1011 ,
b1011 '
b1100111 *
#212000
b1 %
b1 !
b1 2
b1100 #
b1100 ,
b1100 '
b1101000 *
#213000
b10 !
b10 2
b10 %
b1101 #
b1101 ,
b1101 '
b1101001 *
#214000
b11 %
b11 !
b11 2
b1110 #
b1110 ,
b1110 '
b1101010 *
#215000
b100 !
b100 2
b100 %
b1111 #
b1111 ,
b1111 '
b1101011 *
#216000
b110 %
b110 !
b110 2
b0 #
b0 ,
b110 "
b110 +
b110 &
b0 '
b1101100 *
#217000
b111 !
b111 2
b111 %
b1 #
b1 ,
b1 '
b1101101 *
#218000
b1000 %
b1000 !
b1000 2
b10 #
b10 ,
b10 '
b1101110 *
#219000
b1001 !
b1001 2
b1001 %
b11 #
b11 ,
b11 '
b1101111 *
#220000
b1010 %
b1010 !
b1010 2
b100 #
b100 ,
b100 '
b1110000 *
#221000
b1011 !
b1011 2
b1011 %
b101 #
b101 ,
b101 '
b1110001 *
#222000
b1100 %
b1100 !
b1100 2
b110 #
b110 ,
b110 '
b1110010 *
#223000
b1101 !
b1101 2
b1101 %
b111 #
b111 ,
b111 '
b1110011 *
#224000
b1110 %
b1110 !
b1110 2
b1000 #
b1000 ,
b1000 '
b1110100 *
#225000
b1111 !
b1111 2
b1111 %
b1001 #
b1001 ,
b1001 '
b1110101 *
#226000
b0 %
b0 !
b0 2
b1010 #
b1010 ,
b1010 '
b1110110 *
#227000
b1 !
b1 2
b1 %
b1011 #
b1011 ,
b1011 '
b1110111 *
#228000
b10 %
b10 !
b10 2
b1100 #
b1100 ,
b1100 '
b1111000 *
#229000
b11 !
b11 2
b11 %
b1101 #
b1101 ,
b1101 '
b1111001 *
#230000
b100 %
b100 !
b100 2
b1110 #
b1110 ,
b1110 '
b1111010 *
#231000
b101 !
b101 2
b101 %
b1111 #
b1111 ,
b1111 '
b1111011 *
#232000
b111 %
b111 !
b111 2
b0 #
b0 ,
b111 "
b111 +
b111 &
b0 '
b1111100 *
#233000
b1000 !
b1000 2
b1000 %
b1 #
b1 ,
b1 '
b1111101 *
#234000
b1001 %
b1001 !
b1001 2
b10 #
b10 ,
b10 '
b1111110 *
#235000
b1010 !
b1010 2
b1010 %
b11 #
b11 ,
b11 '
b1111111 *
#236000
b1011 %
b1011 !
b1011 2
b100 #
b100 ,
b100 '
b10000000 *
#237000
b1100 !
b1100 2
b1100 %
b101 #
b101 ,
b101 '
b10000001 *
#238000
b1101 %
b1101 !
b1101 2
b110 #
b110 ,
b110 '
b10000010 *
#239000
b1110 !
b1110 2
b1110 %
b111 #
b111 ,
b111 '
b10000011 *
#240000
b1111 %
b1111 !
b1111 2
b1000 #
b1000 ,
b1000 '
b10000100 *
#241000
b0 !
b0 2
b0 %
b1001 #
b1001 ,
b1001 '
b10000101 *
#242000
b1 %
b1 !
b1 2
b1010 #
b1010 ,
b1010 '
b10000110 *
#243000
b10 !
b10 2
b10 %
b1011 #
b1011 ,
b1011 '
b10000111 *
#244000
b11 %
b11 !
b11 2
b1100 #
b1100 ,
b1100 '
b10001000 *
#245000
b100 !
b100 2
b100 %
b1101 #
b1101 ,
b1101 '
b10001001 *
#246000
b101 %
b101 !
b101 2
b1110 #
b1110 ,
b1110 '
b10001010 *
#247000
b110 !
b110 2
b110 %
b1111 #
b1111 ,
b1111 '
b10001011 *
#248000
b1000 %
b1000 !
b1000 2
b0 #
b0 ,
b1000 "
b1000 +
b1000 &
b0 '
b10001100 *
#249000
b1001 !
b1001 2
b1001 %
b1 #
b1 ,
b1 '
b10001101 *
#250000
b1010 %
b1010 !
b1010 2
b10 #
b10 ,
b10 '
b10001110 *
#251000
b1011 !
b1011 2
b1011 %
b11 #
b11 ,
b11 '
b10001111 *
#252000
b1100 %
b1100 !
b1100 2
b100 #
b100 ,
b100 '
b10010000 *
#253000
b1101 !
b1101 2
b1101 %
b101 #
b101 ,
b101 '
b10010001 *
#254000
b1110 %
b1110 !
b1110 2
b110 #
b110 ,
b110 '
b10010010 *
#255000
b1111 !
b1111 2
b1111 %
b111 #
b111 ,
b111 '
b10010011 *
#256000
b0 %
b0 !
b0 2
b1000 #
b1000 ,
b1000 '
b10010100 *
#257000
b1 !
b1 2
b1 %
b1001 #
b1001 ,
b1001 '
b10010101 *
#258000
b10 %
b10 !
b10 2
b1010 #
b1010 ,
b1010 '
b10010110 *
#259000
b11 !
b11 2
b11 %
b1011 #
b1011 ,
b1011 '
b10010111 *
#260000
b100 %
b100 !
b100 2
b1100 #
b1100 ,
b1100 '
b10011000 *
#261000
b101 !
b101 2
b101 %
b1101 #
b1101 ,
b1101 '
b10011001 *
#262000
b110 %
b110 !
b110 2
b1110 #
b1110 ,
b1110 '
b10011010 *
#263000
b111 !
b111 2
b111 %
b1111 #
b1111 ,
b1111 '
b10011011 *
#264000
b1001 %
b1001 !
b1001 2
b0 #
b0 ,
b1001 "
b1001 +
b1001 &
b0 '
b10011100 *
#265000
b1010 !
b1010 2
b1010 %
b1 #
b1 ,
b1 '
b10011101 *
#266000
b1011 %
b1011 !
b1011 2
b10 #
b10 ,
b10 '
b10011110 *
#267000
b1100 !
b1100 2
b1100 %
b11 #
b11 ,
b11 '
b10011111 *
#268000
b1101 %
b1101 !
b1101 2
b100 #
b100 ,
b100 '
b10100000 *
#269000
b1110 !
b1110 2
b1110 %
b101 #
b101 ,
b101 '
b10100001 *
#270000
b1111 %
b1111 !
b1111 2
b110 #
b110 ,
b110 '
b10100010 *
#271000
b0 !
b0 2
b0 %
b111 #
b111 ,
b111 '
b10100011 *
#272000
b1 %
b1 !
b1 2
b1000 #
b1000 ,
b1000 '
b10100100 *
#273000
b10 !
b10 2
b10 %
b1001 #
b1001 ,
b1001 '
b10100101 *
#274000
b11 %
b11 !
b11 2
b1010 #
b1010 ,
b1010 '
b10100110 *
#275000
b100 !
b100 2
b100 %
b1011 #
b1011 ,
b1011 '
b10100111 *
#276000
b101 %
b101 !
b101 2
b1100 #
b1100 ,
b1100 '
b10101000 *
#277000
b110 !
b110 2
b110 %
b1101 #
b1101 ,
b1101 '
b10101001 *
#278000
b111 %
b111 !
b111 2
b1110 #
b1110 ,
b1110 '
b10101010 *
#279000
b1000 !
b1000 2
b1000 %
b1111 #
b1111 ,
b1111 '
b10101011 *
#280000
b1010 %
b1010 !
b1010 2
b0 #
b0 ,
b1010 "
b1010 +
b1010 &
b0 '
b10101100 *
#281000
b1011 !
b1011 2
b1011 %
b1 #
b1 ,
b1 '
b10101101 *
#282000
b1100 %
b1100 !
b1100 2
b10 #
b10 ,
b10 '
b10101110 *
#283000
b1101 !
b1101 2
b1101 %
b11 #
b11 ,
b11 '
b10101111 *
#284000
b1110 %
b1110 !
b1110 2
b100 #
b100 ,
b100 '
b10110000 *
#285000
b1111 !
b1111 2
b1111 %
b101 #
b101 ,
b101 '
b10110001 *
#286000
b0 %
b0 !
b0 2
b110 #
b110 ,
b110 '
b10110010 *
#287000
b1 !
b1 2
b1 %
b111 #
b111 ,
b111 '
b10110011 *
#288000
b10 %
b10 !
b10 2
b1000 #
b1000 ,
b1000 '
b10110100 *
#289000
b11 !
b11 2
b11 %
b1001 #
b1001 ,
b1001 '
b10110101 *
#290000
b100 %
b100 !
b100 2
b1010 #
b1010 ,
b1010 '
b10110110 *
#291000
b101 !
b101 2
b101 %
b1011 #
b1011 ,
b1011 '
b10110111 *
#292000
b110 %
b110 !
b110 2
b1100 #
b1100 ,
b1100 '
b10111000 *
#293000
b111 !
b111 2
b111 %
b1101 #
b1101 ,
b1101 '
b10111001 *
#294000
b1000 %
b1000 !
b1000 2
b1110 #
b1110 ,
b1110 '
b10111010 *
#295000
b1001 !
b1001 2
b1001 %
b1111 #
b1111 ,
b1111 '
b10111011 *
#296000
b1011 %
b1011 !
b1011 2
b0 #
b0 ,
b1011 "
b1011 +
b1011 &
b0 '
b10111100 *
#297000
b1100 !
b1100 2
b1100 %
b1 #
b1 ,
b1 '
b10111101 *
#298000
b1101 %
b1101 !
b1101 2
b10 #
b10 ,
b10 '
b10111110 *
#299000
b1110 !
b1110 2
b1110 %
b11 #
b11 ,
b11 '
b10111111 *
#300000
b1111 %
b1111 !
b1111 2
b100 #
b100 ,
b100 '
b11000000 *
#301000
b0 !
b0 2
b0 %
b101 #
b101 ,
b101 '
b11000001 *
#302000
b1 %
b1 !
b1 2
b110 #
b110 ,
b110 '
b11000010 *
#303000
b10 !
b10 2
b10 %
b111 #
b111 ,
b111 '
b11000011 *
#304000
b11 %
b11 !
b11 2
b1000 #
b1000 ,
b1000 '
b11000100 *
#305000
b100 !
b100 2
b100 %
b1001 #
b1001 ,
b1001 '
b11000101 *
#306000
b101 %
b101 !
b101 2
b1010 #
b1010 ,
b1010 '
b11000110 *
#307000
b110 !
b110 2
b110 %
b1011 #
b1011 ,
b1011 '
b11000111 *
#308000
b111 %
b111 !
b111 2
b1100 #
b1100 ,
b1100 '
b11001000 *
#309000
b1000 !
b1000 2
b1000 %
b1101 #
b1101 ,
b1101 '
b11001001 *
#310000
b1001 %
b1001 !
b1001 2
b1110 #
b1110 ,
b1110 '
b11001010 *
#311000
b1010 !
b1010 2
b1010 %
b1111 #
b1111 ,
b1111 '
b11001011 *
#312000
b1100 %
b1100 !
b1100 2
b0 #
b0 ,
b1100 "
b1100 +
b1100 &
b0 '
b11001100 *
#313000
b1101 !
b1101 2
b1101 %
b1 #
b1 ,
b1 '
b11001101 *
#314000
b1110 %
b1110 !
b1110 2
b10 #
b10 ,
b10 '
b11001110 *
#315000
b1111 !
b1111 2
b1111 %
b11 #
b11 ,
b11 '
b11001111 *
#316000
b0 %
b0 !
b0 2
b100 #
b100 ,
b100 '
b11010000 *
#317000
b1 !
b1 2
b1 %
b101 #
b101 ,
b101 '
b11010001 *
#318000
b10 %
b10 !
b10 2
b110 #
b110 ,
b110 '
b11010010 *
#319000
b11 !
b11 2
b11 %
b111 #
b111 ,
b111 '
b11010011 *
#320000
b100 %
b100 !
b100 2
b1000 #
b1000 ,
b1000 '
b11010100 *
#321000
b101 !
b101 2
b101 %
b1001 #
b1001 ,
b1001 '
b11010101 *
#322000
b110 %
b110 !
b110 2
b1010 #
b1010 ,
b1010 '
b11010110 *
#323000
b111 !
b111 2
b111 %
b1011 #
b1011 ,
b1011 '
b11010111 *
#324000
b1000 %
b1000 !
b1000 2
b1100 #
b1100 ,
b1100 '
b11011000 *
#325000
b1001 !
b1001 2
b1001 %
b1101 #
b1101 ,
b1101 '
b11011001 *
#326000
b1010 %
b1010 !
b1010 2
b1110 #
b1110 ,
b1110 '
b11011010 *
#327000
b1011 !
b1011 2
b1011 %
b1111 #
b1111 ,
b1111 '
b11011011 *
#328000
b1101 %
b1101 !
b1101 2
b0 #
b0 ,
b1101 "
b1101 +
b1101 &
b0 '
b11011100 *
#329000
b1110 !
b1110 2
b1110 %
b1 #
b1 ,
b1 '
b11011101 *
#330000
b1111 %
b1111 !
b1111 2
b10 #
b10 ,
b10 '
b11011110 *
#331000
b0 !
b0 2
b0 %
b11 #
b11 ,
b11 '
b11011111 *
#332000
b1 %
b1 !
b1 2
b100 #
b100 ,
b100 '
b11100000 *
#333000
b10 !
b10 2
b10 %
b101 #
b101 ,
b101 '
b11100001 *
#334000
b11 %
b11 !
b11 2
b110 #
b110 ,
b110 '
b11100010 *
#335000
b100 !
b100 2
b100 %
b111 #
b111 ,
b111 '
b11100011 *
#336000
b101 %
b101 !
b101 2
b1000 #
b1000 ,
b1000 '
b11100100 *
#337000
b110 !
b110 2
b110 %
b1001 #
b1001 ,
b1001 '
b11100101 *
#338000
b111 %
b111 !
b111 2
b1010 #
b1010 ,
b1010 '
b11100110 *
#339000
b1000 !
b1000 2
b1000 %
b1011 #
b1011 ,
b1011 '
b11100111 *
#340000
b1001 %
b1001 !
b1001 2
b1100 #
b1100 ,
b1100 '
b11101000 *
#341000
b1010 !
b1010 2
b1010 %
b1101 #
b1101 ,
b1101 '
b11101001 *
#342000
b1011 %
b1011 !
b1011 2
b1110 #
b1110 ,
b1110 '
b11101010 *
#343000
b1100 !
b1100 2
b1100 %
b1111 #
b1111 ,
b1111 '
b11101011 *
#344000
b1110 %
b1110 !
b1110 2
b0 #
b0 ,
b1110 "
b1110 +
b1110 &
b0 '
b11101100 *
#345000
b1111 !
b1111 2
b1111 %
b1 #
b1 ,
b1 '
b11101101 *
#346000
b0 %
b0 !
b0 2
b10 #
b10 ,
b10 '
b11101110 *
#347000
b1 !
b1 2
b1 %
b11 #
b11 ,
b11 '
b11101111 *
#348000
b10 %
b10 !
b10 2
b100 #
b100 ,
b100 '
b11110000 *
#349000
b11 !
b11 2
b11 %
b101 #
b101 ,
b101 '
b11110001 *
#350000
b100 %
b100 !
b100 2
b110 #
b110 ,
b110 '
b11110010 *
#351000
b101 !
b101 2
b101 %
b111 #
b111 ,
b111 '
b11110011 *
#352000
b110 %
b110 !
b110 2
b1000 #
b1000 ,
b1000 '
b11110100 *
#353000
b111 !
b111 2
b111 %
b1001 #
b1001 ,
b1001 '
b11110101 *
#354000
b1000 %
b1000 !
b1000 2
b1010 #
b1010 ,
b1010 '
b11110110 *
#355000
b1001 !
b1001 2
b1001 %
b1011 #
b1011 ,
b1011 '
b11110111 *
#356000
b1010 %
b1010 !
b1010 2
b1100 #
b1100 ,
b1100 '
b11111000 *
#357000
b1011 !
b1011 2
b1011 %
b1101 #
b1101 ,
b1101 '
b11111001 *
#358000
b1100 %
b1100 !
b1100 2
b1110 #
b1110 ,
b1110 '
b11111010 *
#359000
b1101 !
b1101 2
b1101 %
b1111 #
b1111 ,
b1111 '
b11111011 *
#360000
b1111 %
b1111 !
b1111 2
b0 #
b0 ,
b1111 "
b1111 +
b1111 &
b0 '
b11111100 *
#361000
b0 !
b0 2
b0 %
b1 #
b1 ,
b1 '
b11111101 *
#362000
b1 %
b1 !
b1 2
b10 #
b10 ,
b10 '
b11111110 *
#363000
b10 !
b10 2
b10 %
b11 #
b11 ,
b11 '
b11111111 *
#364000
b11 %
b11 !
b11 2
b100 #
b100 ,
b100 '
b100000000 *
#365000
b100 !
b100 2
b100 %
b101 #
b101 ,
b101 '
b100000001 *
#366000
b101 %
b101 !
b101 2
b110 #
b110 ,
b110 '
b100000010 *
#367000
b110 !
b110 2
b110 %
b111 #
b111 ,
b111 '
b100000011 *
#368000
b111 %
b111 !
b111 2
b1000 #
b1000 ,
b1000 '
b100000100 *
#369000
b1000 !
b1000 2
b1000 %
b1001 #
b1001 ,
b1001 '
b100000101 *
#370000
b1001 %
b1001 !
b1001 2
b1010 #
b1010 ,
b1010 '
b100000110 *
#371000
b1010 !
b1010 2
b1010 %
b1011 #
b1011 ,
b1011 '
b100000111 *
#372000
b1011 %
b1011 !
b1011 2
b1100 #
b1100 ,
b1100 '
b100001000 *
#373000
b1100 !
b1100 2
b1100 %
b1101 #
b1101 ,
b1101 '
b100001001 *
#374000
b1101 %
b1101 !
b1101 2
b1110 #
b1110 ,
b1110 '
b100001010 *
#375000
b1110 !
b1110 2
b1110 %
b1111 #
b1111 ,
b1111 '
b100001011 *
#376000
b0 %
b0 !
b0 2
b0 #
b0 ,
b0 "
b0 +
b1 $
b1 -
b1 )
b0 &
b0 '
b100001100 *
#377000
b1111 !
b1111 2
b1111 %
b1 #
b1 ,
b1 '
b100001101 *
#378000
b1110 %
b1110 !
b1110 2
b10 #
b10 ,
b10 '
b100001110 *
#379000
b1101 !
b1101 2
b1101 %
b11 #
b11 ,
b11 '
b100001111 *
#380000
b1100 %
b1100 !
b1100 2
b100 #
b100 ,
b100 '
b100010000 *
