Lab002/src/ALU.v
`timescale 1ns / 1ps
// ============================================================
// Lab02 - ALU de 4 bits (logica puramente combinacional)
//
//   OP | Operacion
//   00 | A + B   (suma, sin acarreo: resultado modulo 16)
//   01 | A - B   (resta, complemento a 2: 3 - 5 = 1110)
//   10 | A & B   (AND bit a bit)
//   11 | A | B   (OR bit a bit)
//
// No tiene reloj ni registros: la salida depende solo de las
// entradas actuales. Todos los casos del case asignan OUTT,
// por lo que no se infieren latches.
// ============================================================
module ALU (
    input      [3:0] A,
    input      [3:0] B,
    input      [1:0] OP,
    output reg [3:0] OUTT
);

    localparam [1:0] SUM_OP = 2'b00;
    localparam [1:0] RES_OP = 2'b01;
    localparam [1:0] AND_OP = 2'b10;
    localparam [1:0] OR_OP  = 2'b11;

    always @(*) begin
        case (OP)
            SUM_OP:  OUTT = A + B;
            RES_OP:  OUTT = A - B;
            AND_OP:  OUTT = A & B;
            OR_OP:   OUTT = A | B;
            default: OUTT = 4'b0000;
        endcase
    end

endmodule

Lab002/src/datapath.v
`timescale 1ns / 1ps
// ============================================================
// Lab02 - Modulo superior (datapath) de la ALU de 4 bits
//  - Registros A y B: se cargan con SW mientras BTN0 / BTN1 esten presionados
//  - Registro C (opcode): BTN2 invierte C[0], BTN3 invierte C[1]
//    y el valor se conserva al soltar los botones
//  - La ALU (combinacional) esta en un modulo aparte
//  - LED RGB indica la operacion almacenada en C
//
// Sin modulo de antirrebote: BTN2 y BTN3 se muestrean cada N_TICK ciclos
// (10 ms a 125 MHz). El rebote dura menos que eso, asi que entre dos
// muestras solo se ve un cambio por pulsacion.
// ============================================================
module datapath #(
    parameter integer N_TICK = 1250000      // 10 ms a 125 MHz
)(
    input            clk,
    input      [3:0] SW,
    input      [3:0] BTNS,
    output     [3:0] LED,
    output reg       LED_R, LED_G, LED_B
);

    localparam [1:0] SUM_OP = 2'b00;
    localparam [1:0] RES_OP = 2'b01;
    localparam [1:0] AND_OP = 2'b10;
    localparam [1:0] OR_OP  = 2'b11;

    //------------------------------------------------
    // Registros del sistema (valores iniciales = estado de arranque)
    //------------------------------------------------
    reg [3:0] A = 4'd0;
    reg [3:0] B = 4'd0;
    reg [1:0] C = SUM_OP;
    wire [3:0] Z;

    //------------------------------------------------
    // Sincronizador de 2 flip-flops para los botones
    //------------------------------------------------
    reg [3:0] btn_s0 = 4'b0000;
    reg [3:0] btn_s1 = 4'b0000;

    always @(posedge clk) begin
        btn_s0 <= BTNS;
        btn_s1 <= btn_s0;
    end

    //------------------------------------------------
    // Registros A y B
    //------------------------------------------------
    always @(posedge clk) begin
        if (btn_s1[0]) A <= SW;
        if (btn_s1[1]) B <= SW;
    end

    //------------------------------------------------
    // Base de tiempo para muestrear BTN2 y BTN3
    //------------------------------------------------
    integer cnt  = 0;
    reg     tick = 1'b0;

    always @(posedge clk) begin
        if (cnt == N_TICK - 1) begin
            cnt  <= 0;
            tick <= 1'b1;
        end else begin
            cnt  <= cnt + 1;
            tick <= 1'b0;
        end
    end

    //------------------------------------------------
    // Registro del codigo de operacion C
    // En cada tick se compara la muestra actual con la anterior:
    // si paso de 0 a 1 (pulsacion), se invierte el bit correspondiente
    //------------------------------------------------
    reg [3:2] btn_m = 2'b00;   // muestra anterior de BTN3, BTN2

    always @(posedge clk) begin
        if (tick) begin
            if (btn_s1[2] & ~btn_m[2]) C[0] <= ~C[0];   // BTN2 -> bit 0
            if (btn_s1[3] & ~btn_m[3]) C[1] <= ~C[1];   // BTN3 -> bit 1
            btn_m <= btn_s1[3:2];
        end
    end

    //------------------------------------------------
    // ALU combinacional (modulo independiente)
    //------------------------------------------------
    ALU calll (
        .A    (A),
        .B    (B),
        .OP   (C),
        .OUTT (Z)
    );

    assign LED = Z;

    //------------------------------------------------
    // Indicador de operacion en el LED RGB
    //------------------------------------------------
    always @(*) begin
        case (C)
            SUM_OP:  {LED_R, LED_G, LED_B} = 3'b010;   // Verde
            RES_OP:  {LED_R, LED_G, LED_B} = 3'b100;   // Rojo
            AND_OP:  {LED_R, LED_G, LED_B} = 3'b001;   // Azul
            OR_OP:   {LED_R, LED_G, LED_B} = 3'b011;   // Cian (G + B)
            default: {LED_R, LED_G, LED_B} = 3'b000;
        endcase
    end

endmodule

Lab002/sim/tb_datapath.v
`timescale 1ns / 1ps
// ============================================================
// Testbench autoverificable del datapath (Lab02)
//  - Reloj de 125 MHz (8 ns), igual al de la Zybo Z7
//  - N_TICK reducido a 20 ciclos para que la simulacion sea corta
//  - Las pulsaciones de BTN2/BTN3 incluyen rebote simulado
// ============================================================
module tb_datapath;

    localparam integer N_TICK = 20;

    reg        clk  = 1'b0;
    reg  [3:0] SW   = 4'd0;
    reg  [3:0] BTNS = 4'd0;
    wire [3:0] LED;
    wire       LED_R, LED_G, LED_B;

    integer errores = 0;

    datapath #(.N_TICK(N_TICK)) dut (
        .clk   (clk),
        .SW    (SW),
        .BTNS  (BTNS),
        .LED   (LED),
        .LED_R (LED_R),
        .LED_G (LED_G),
        .LED_B (LED_B)
    );

    always #4 clk = ~clk;   // 125 MHz

    //------------------------------------------------
    // Esperar varios periodos de muestreo
    //------------------------------------------------
    task esperar;
        begin
            repeat (5 * N_TICK) @(posedge clk);
        end
    endtask

    //------------------------------------------------
    // Pulsacion con rebote: el boton oscila unos ciclos
    // al presionar y al soltar
    //------------------------------------------------
    task press_btn;
        input integer idx;
        integer k;
        begin
            for (k = 0; k < 4; k = k + 1) begin
                BTNS[idx] = 1; repeat (3) @(posedge clk);
                BTNS[idx] = 0; repeat (2) @(posedge clk);
            end
            BTNS[idx] = 1;
            esperar;
            for (k = 0; k < 4; k = k + 1) begin
                BTNS[idx] = 0; repeat (3) @(posedge clk);
                BTNS[idx] = 1; repeat (2) @(posedge clk);
            end
            BTNS[idx] = 0;
            esperar;
        end
    endtask

    //------------------------------------------------
    // Comparacion con el valor esperado
    //------------------------------------------------
    task verificar;
        input [8*16-1:0] caso;
        input [3:0]      a_esp, b_esp;
        input [1:0]      c_esp;
        input [3:0]      led_esp;
        input [2:0]      rgb_esp;     // {R, G, B}
        begin
            if (dut.A !== a_esp || dut.B !== b_esp || dut.C !== c_esp ||
                LED !== led_esp || {LED_R, LED_G, LED_B} !== rgb_esp) begin
                $display("ERROR %s: A=%0d B=%0d C=%b LED=%0d RGB=%b | esperado A=%0d B=%0d C=%b LED=%0d RGB=%b",
                         caso, dut.A, dut.B, dut.C, LED, {LED_R, LED_G, LED_B},
                         a_esp, b_esp, c_esp, led_esp, rgb_esp);
                errores = errores + 1;
            end else
                $display("OK    %s: A=%0d B=%0d C=%b LED=%0d RGB=%b",
                         caso, dut.A, dut.B, dut.C, LED, {LED_R, LED_G, LED_B});
        end
    endtask

    //------------------------------------------------
    // Estimulos
    //------------------------------------------------
    initial begin
        $dumpfile("tb_datapath.vcd");
        $dumpvars(0, tb_datapath);

        esperar;

        // Carga de operandos
        SW = 4'd5;  press_btn(0);
        SW = 4'd3;  press_btn(1);

        // Mover los switches sin cargar: A y B no deben cambiar
        SW = 4'd15; esperar;
        verificar("SUMA  5+3      ", 4'd5, 4'd3, 2'b00, 4'd8,  3'b010);

        press_btn(2);   // C = 01
        verificar("RESTA 5-3      ", 4'd5, 4'd3, 2'b01, 4'd2,  3'b100);

        press_btn(3);   // C = 11
        verificar("OR    5|3      ", 4'd5, 4'd3, 2'b11, 4'd7,  3'b011);

        press_btn(2);   // C = 10
        verificar("AND   5&3      ", 4'd5, 4'd3, 2'b10, 4'd1,  3'b001);

        // Nuevos operandos, con la operacion AND todavia seleccionada
        SW = 4'd9;  press_btn(0);
        SW = 4'd6;  press_btn(1);
        verificar("AND   9&6      ", 4'd9, 4'd6, 2'b10, 4'd0,  3'b001);

        press_btn(2);   // C = 11
        verificar("OR    9|6      ", 4'd9, 4'd6, 2'b11, 4'd15, 3'b011);

        press_btn(3);   // C = 01
        verificar("RESTA 9-6      ", 4'd9, 4'd6, 2'b01, 4'd3,  3'b100);

        press_btn(2);   // C = 00
        verificar("SUMA  9+6      ", 4'd9, 4'd6, 2'b00, 4'd15, 3'b010);

        $display("--------------------------------------------");
        if (errores == 0) $display("DATAPATH: PASO");
        else              $display("DATAPATH: FALLO - %0d errores", errores);
        $display("--------------------------------------------");
        $finish;
    end

endmodule

Lab002/sim/tb_datapath.vcd
$date
	Mon Sep 28 21:55:08 2026
$end
$version
	Icarus Verilog
$end
$timescale
	1ps
$end
$scope module tb_datapath $end
$var wire 1 ! LED_R $end
$var wire 1 " LED_G $end
$var wire 1 # LED_B $end
$var wire 4 $ LED [3:0] $end
$var parameter 32 % N_TICK $end
$var reg 4 & BTNS [3:0] $end
$var reg 4 ' SW [3:0] $end
$var reg 1 ( clk $end
$var integer 32 ) errores [31:0] $end
$scope module dut $end
$var wire 4 * BTNS [3:0] $end
$var wire 4 + LED [3:0] $end
$var wire 4 , SW [3:0] $end
$var wire 1 ( clk $end
$var wire 4 - Z [3:0] $end
$var parameter 2 . AND_OP $end
$var parameter 32 / N_TICK $end
$var parameter 2 0 OR_OP $end
$var parameter 2 1 RES_OP $end
$var parameter 2 2 SUM_OP $end
$var reg 4 3 A [3:0] $end
$var reg 4 4 B [3:0] $end
$var reg 2 5 C [1:0] $end
$var reg 1 # LED_B $end
$var reg 1 " LED_G $end
$var reg 1 ! LED_R $end
$var reg 2 6 btn_m [3:2] $end
$var reg 4 7 btn_s0 [3:0] $end
$var reg 4 8 btn_s1 [3:0] $end
$var reg 1 9 tick $end
$var integer 32 : cnt [31:0] $end
$scope module calll $end
$var wire 4 ; A [3:0] $end
$var wire 4 < B [3:0] $end
$var wire 2 = OP [1:0] $end
$var parameter 2 > AND_OP $end
$var parameter 2 ? OR_OP $end
$var parameter 2 @ RES_OP $end
$var parameter 2 A SUM_OP $end
$var reg 4 B OUTT [3:0] $end
$upscope $end
$upscope $end
$scope task esperar $end
$upscope $end
$scope task press_btn $end
$var integer 32 C idx [31:0] $end
$var integer 32 D k [31:0] $end
$upscope $end
$scope task verificar $end
$var reg 4 E a_esp [3:0] $end
$var reg 4 F b_esp [3:0] $end
$var reg 2 G c_esp [1:0] $end
$var reg 128 H caso [127:0] $end
$var reg 4 I led_esp [3:0] $end
$var reg 3 J rgb_esp [2:0] $end
$upscope $end
$upscope $end
$enddefinitions $end
$comment Show the parameter values. $end
$dumpall
b0 A
b1 @
b11 ?
b10 >
b0 2
b1 1
b11 0
b10100 /
b10 .
b10100 %
$end
#0
$dumpvars
bx J
bx I
bx H
bx G
bx F
bx E
bx D
bx C
b0 B
b0 =
b0 <
b0 ;
b0 :
09
b0 8
b0 7
b0 6
b0 5
b0 4
b0 3
b0 -
b0 ,
b0 +
b0 *
b0 )
0(
b0 '
b0 &
b0 $
0#
1"
0!
$end
#4000
b1 :
1(
#8000
0(
#12000
b10 :
1(
#16000
0(
#20000
b11 :
1(
#24000
0(
#28000
b100 :
1(
#32000
0(
#36000
b101 :
1(
#40000
0(
#44000
b110 :
1(
#48000
0(
#52000
b111 :
1(
#56000
0(
#60000
b1000 :
1(
#64000
0(
#68000
b1001 :
1(
#72000
0(
#76000
b1010 :
1(
#80000
0(
#84000
b1011 :
1(
#88000
0(
#92000
b1100 :
1(
#96000
0(
#100000
b1101 :
1(
#104000
0(
#108000
b1110 :
1(
#112000
0(
#116000
b1111 :
1(
#120000
0(
#124000
b10000 :
1(
#128000
0(
#132000
b10001 :
1(
#136000
0(
#140000
b10010 :
1(
#144000
0(
#148000
b10011 :
1(
#152000
0(
#156000
19
b0 :
1(
#160000
0(
#164000
09
b1 :
1(
#168000
0(
#172000
b10 :
1(
#176000
0(
#180000
b11 :
1(
#184000
0(
#188000
b100 :
1(
#192000
0(
#196000
b101 :
1(
#200000
0(
#204000
b110 :
1(
#208000
0(
#212000
b111 :
1(
#216000
0(
#220000
b1000 :
1(
#224000
0(
#228000
b1001 :
1(
#232000
0(
#236000
b1010 :
1(
#240000
0(
#244000
b1011 :
1(
#248000
0(
#252000
b1100 :
1(
#256000
0(
#260000
b1101 :
1(
#264000
0(
#268000
b1110 :
1(
#272000
0(
#276000
b1111 :
1(
#280000
0(
#284000
b10000 :
1(
#288000
0(
#292000
b10001 :
1(
#296000
0(
#300000
b10010 :
1(
#304000
0(
#308000
b10011 :
1(
#312000
0(
#316000
19
b0 :
1(
#320000
0(
#324000
09
b1 :
1(
#328000
0(
#332000
b10 :
1(
#336000
0(
#340000
b11 :
1(
#344000
0(
#348000
b100 :
1(
#352000
0(
#356000
b101 :
1(
#360000
0(
#364000
b110 :
1(
#368000
0(
#372000
b111 :
1(
#376000
0(
#380000
b1000 :
1(
#384000
0(
#388000
b1001 :
1(
#392000
0(
#396000
b1010 :
1(
#400000
0(
#404000
b1011 :
1(
#408000
0(
#412000
b1100 :
1(
#416000
0(
#420000
b1101 :
1(
#424000
0(
#428000
b1110 :
1(
#432000
0(
#436000
b1111 :
1(
#440000
0(
#444000
b10000 :
1(
#448000
0(
#452000
b10001 :
1(
#456000
0(
#460000
b10010 :
1(
#464000
0(
#468000
b10011 :
1(
#472000
0(
#476000
19
b0 :
1(
#480000
0(
#484000
09
b1 :
1(
#488000
0(
#492000
b10 :
1(
#496000
0(
#500000
b11 :
1(
#504000
0(
#508000
b100 :
1(
#512000
0(
#516000
b101 :
1(
#520000
0(
#524000
b110 :
1(
#528000
0(
#532000
b111 :
1(
#536000
0(
#540000
b1000 :
1(
#544000
0(
#548000
b1001 :
1(
#552000
0(
#556000
b1010 :
1(
#560000
0(
#564000
b1011 :
1(
#568000
0(
#572000
b1100 :
1(
#576000
0(
#580000
b1101 :
1(
#584000
0(
#588000
b1110 :
1(
#592000
0(
#596000
b1111 :
1(
#600000
0(
#604000
b10000 :
1(
#608000
0(
#612000
b10001 :
1(
#616000
0(
#620000
b10010 :
1(
#624000
0(
#628000
b10011 :
1(
#632000
0(
#636000
19
b0 :
1(
#640000
0(
#644000
09
b1 :
1(
#648000
0(
#652000
b10 :
1(
#656000
0(
#660000
b11 :
1(
#664000
0(
#668000
b100 :
1(
#672000
0(
#676000
b101 :
1(
#680000
0(
#684000
b110 :
1(
#688000
0(
#692000
b111 :
1(
#696000
0(
#700000
b1000 :
1(
#704000
0(
#708000
b1001 :
1(
#712000
0(
#716000
b1010 :
1(
#720000
0(
#724000
b1011 :
1(
#728000
0(
#732000
b1100 :
1(
#736000
0(
#740000
b1101 :
1(
#744000
0(
#748000
b1110 :
1(
#752000
0(
#756000
b1111 :
1(
#760000
0(
#764000
b10000 :
1(
#768000
0(
#772000
b10001 :
1(
#776000
0(
#780000
b10010 :
1(
#784000
0(
#788000
b10011 :
1(
#792000
0(
#796000
19
b0 :
b1 &
b1 *
b0 D
b0 C
b101 '
b101 ,
1(
#800000
0(
#804000
b1 7
09
b1 :
1(
#808000
0(
#812000
b10 :
b1 8
1(
#816000
0(
#820000
b101 $
b101 +
b101 -
b101 B
b0 7
b101 3
b101 ;
b11 :
b0 &
b0 *
1(
#824000
0(
#828000
b100 :
b0 8
1(
#832000
0(
#836000
b1 7
b101 :
b1 &
b1 *
b1 D
1(
#840000
0(
#844000
b110 :
b1 8
1(
#848000
0(
#852000
b111 :
1(
#856000
0(
#860000
b1000 :
b0 &
b0 *
1(
#864000
0(
#868000
b0 7
b1001 :
1(
#872000
0(
#876000
b1010 :
b0 8
b1 &
b1 *
b10 D
1(
#880000
0(
#884000
b1 7
b1011 :
1(
#888000
0(
#892000
b1100 :
b1 8
1(
#896000
0(
#900000
b0 7
b1101 :
b0 &
b0 *
1(
#904000
0(
#908000
b1110 :
b0 8
1(
#912000
0(
#916000
b1 7
b1111 :
b1 &
b1 *
b11 D
1(
#920000
0(
#924000
b10000 :
b1 8
1(
#928000
0(
#932000
b10001 :
1(
#936000
0(
#940000
b10010 :
b0 &
b0 *
1(
#944000
0(
#948000
b0 7
b10011 :
1(
#952000
0(
#956000
19
b0 :
b0 8
b1 &
b1 *
b100 D
1(
#960000
0(
#964000
b1 7
09
b1 :
1(
#968000
0(
#972000
b10 :
b1 8
1(
#976000
0(
#980000
b11 :
1(
#984000
0(
#988000
b100 :
1(
#992000
0(
#996000
b101 :
1(
#1000000
0(
#1004000
b110 :
1(
#1008000
0(
#1012000
b111 :
1(
#1016000
0(
#1020000
b1000 :
1(
#1024000
0(
#1028000
b1001 :
1(
#1032000
0(
#1036000
b1010 :
1(
#1040000
0(
#1044000
b1011 :
1(
#1048000
0(
#1052000
b1100 :
1(
#1056000
0(
#1060000
b1101 :
1(
#1064000
0(
#1068000
b1110 :
1(
#1072000
0(
#1076000
b1111 :
1(
#1080000
0(
#1084000
b10000 :
1(
#1088000
0(
#1092000
b10001 :
1(
#1096000
0(
#1100000
b10010 :
1(
#1104000
0(
#1108000
b10011 :
1(
#1112000
0(
#1116000
19
b0 :
1(
#1120000
0(
#1124000
09
b1 :
1(
#1128000
0(
#1132000
b10 :
1(
#1136000
0(
#1140000
b11 :
1(
#1144000
0(
#1148000
b100 :
1(
#1152000
0(
#1156000
b101 :
1(
#1160000
0(
#1164000
b110 :
1(
#1168000
0(
#1172000
b111 :
1(
#1176000
0(
#1180000
b1000 :
1(
#1184000
0(
#1188000
b1001 :
1(
#1192000
0(
#1196000
b1010 :
1(
#1200000
0(
#1204000
b1011 :
1(
#1208000
0(
#1212000
b1100 :
1(
#1216000
0(
#1220000
b1101 :
1(
#1224000
0(
#1228000
b1110 :
1(
#1232000
0(
#1236000
b1111 :
1(
#1240000
0(
#1244000
b10000 :
1(
#1248000
0(
#1252000
b10001 :
1(
#1256000
0(
#1260000
b10010 :
1(
#1264000
0(
#1268000
b10011 :
1(
#1272000
0(
#1276000
19
b0 :
1(
#1280000
0(
#1284000
09
b1 :
1(
#1288000
0(
#1292000
b10 :
1(
#1296000
0(
#1300000
b11 :
1(
#1304000
0(
#1308000
b100 :
1(
#1312000
0(
#1316000
b101 :
1(
#1320000
0(
#1324000
b110 :
1(
#1328000
0(
#1332000
b111 :
1(
#1336000
0(
#1340000
b1000 :
1(
#1344000
0(
#1348000
b1001 :
1(
#1352000
0(
#1356000
b1010 :
1(
#1360000
0(
#1364000
b1011 :
1(
#1368000
0(
#1372000
b1100 :
1(
#1376000
0(
#1380000
b1101 :
1(
#1384000
0(
#1388000
b1110 :
1(
#1392000
0(
#1396000
b1111 :
1(
#1400000
0(
#1404000
b10000 :
1(
#1408000
0(
#1412000
b10001 :
1(
#1416000
0(
#1420000
b10010 :
1(
#1424000
0(
#1428000
b10011 :
1(
#1432000
0(
#1436000
19
b0 :
1(
#1440000
0(
#1444000
09
b1 :
1(
#1448000
0(
#1452000
b10 :
1(
#1456000
0(
#1460000
b11 :
1(
#1464000
0(
#1468000
b100 :
1(
#1472000
0(
#1476000
b101 :
1(
#1480000
0(
#1484000
b110 :
1(
#1488000
0(
#1492000
b111 :
1(
#1496000
0(
#1500000
b1000 :
1(
#1504000
0(
#1508000
b1001 :
1(
#1512000
0(
#1516000
b1010 :
1(
#1520000
0(
#1524000
b1011 :
1(
#1528000
0(
#1532000
b1100 :
1(
#1536000
0(
#1540000
b1101 :
1(
#1544000
0(
#1548000
b1110 :
1(
#1552000
0(
#1556000
b1111 :
1(
#1560000
0(
#1564000
b10000 :
1(
#1568000
0(
#1572000
b10001 :
1(
#1576000
0(
#1580000
b10010 :
1(
#1584000
0(
#1588000
b10011 :
1(
#1592000
0(
#1596000
19
b0 :
1(
#1600000
0(
#1604000
09
b1 :
1(
#1608000
0(
#1612000
b10 :
1(
#1616000
0(
#1620000
b11 :
1(
#1624000
0(
#1628000
b100 :
1(
#1632000
0(
#1636000
b101 :
1(
#1640000
0(
#1644000
b110 :
1(
#1648000
0(
#1652000
b111 :
1(
#1656000
0(
#1660000
b1000 :
1(
#1664000
0(
#1668000
b1001 :
1(
#1672000
0(
#1676000
b1010 :
1(
#1680000
0(
#1684000
b1011 :
1(
#1688000
0(
#1692000
b1100 :
1(
#1696000
0(
#1700000
b1101 :
1(
#1704000
0(
#1708000
b1110 :
1(
#1712000
0(
#1716000
b1111 :
1(
#1720000
0(
#1724000
b10000 :
1(
#1728000
0(
#1732000
b10001 :
1(
#1736000
0(
#1740000
b10010 :
1(
#1744000
0(
#1748000
b10011 :
1(
#1752000
0(
#1756000
19
b0 :
b0 &
b0 *
b0 D
1(
#1760000
0(
#1764000
b0 7
09
b1 :
1(
#1768000
0(
#1772000
b10 :
b0 8
1(
#1776000
0(
#1780000
b1 7
b11 :
b1 &
b1 *
1(
#1784000
0(
#1788000
b100 :
b1 8
1(
#1792000
0(
#1796000
b0 7
b101 :
b0 &
b0 *
b1 D
1(
#1800000
0(
#1804000
b110 :
b0 8
1(
#1808000
0(
#1812000
b111 :
1(
#1816000
0(
#1820000
b1000 :
b1 &
b1 *
1(
#1824000
0(
#1828000
b1 7
b1001 :
1(
#1832000
0(
#1836000
b1010 :
b1 8
b0 &
b0 *
b10 D
1(
#1840000
0(
#1844000
b0 7
b1011 :
1(
#1848000
0(
#1852000
b1100 :
b0 8
1(
#1856000
0(
#1860000
b1 7
b1101 :
b1 &
b1 *
1(
#1864000
0(
#1868000
b1110 :
b1 8
1(
#1872000
0(
#1876000
b0 7
b1111 :
b0 &
b0 *
b11 D
1(
#1880000
0(
#1884000
b10000 :
b0 8
1(
#1888000
0(
#1892000
b10001 :
1(
#1896000
0(
#1900000
b10010 :
b1 &
b1 *
1(
#1904000
0(
#1908000
b1 7
b10011 :
1(
#1912000
0(
#1916000
19
b0 :
b1 8
b0 &
b0 *
b100 D
1(
#1920000
0(
#1924000
b0 7
09
b1 :
1(
#1928000
0(
#1932000
b10 :
b0 8
1(
#1936000
0(
#1940000
b11 :
1(
#1944000
0(
#1948000
b100 :
1(
#1952000
0(
#1956000
b101 :
1(
#1960000
0(
#1964000
b110 :
1(
#1968000
0(
#1972000
b111 :
1(
#1976000
0(
#1980000
b1000 :
1(
#1984000
0(
#1988000
b1001 :
1(
#1992000
0(
#1996000
b1010 :
1(
#2000000
0(
#2004000
b1011 :
1(
#2008000
0(
#2012000
b1100 :
1(
#2016000
0(
#2020000
b1101 :
1(
#2024000
0(
#2028000
b1110 :
1(
#2032000
0(
#2036000
b1111 :
1(
#2040000
0(
#2044000
b10000 :
1(
#2048000
0(
#2052000
b10001 :
1(
#2056000
0(
#2060000
b10010 :
1(
#2064000
0(
#2068000
b10011 :
1(
#2072000
0(
#2076000
19
b0 :
1(
#2080000
0(
#2084000
09
b1 :
1(
#2088000
0(
#2092000
b10 :
1(
#2096000
0(
#2100000
b11 :
1(
#2104000
0(
#2108000
b100 :
1(
#2112000
0(
#2116000
b101 :
1(
#2120000
0(
#2124000
b110 :
1(
#2128000
0(
#2132000
b111 :
1(
#2136000
0(
#2140000
b1000 :
1(
#2144000
0(
#2148000
b1001 :
1(
#2152000
0(
#2156000
b1010 :
1(
#2160000
0(
#2164000
b1011 :
1(
#2168000
0(
#2172000
b1100 :
1(
#2176000
0(
#2180000
b1101 :
1(
#2184000
0(
#2188000
b1110 :
1(
#2192000
0(
#2196000
b1111 :
1(
#2200000
0(
#2204000
b10000 :
1(
#2208000
0(
#2212000
b10001 :
1(
#2216000
0(
#2220000
b10010 :
1(
#2224000
0(
#2228000
b10011 :
1(
#2232000
0(
#2236000
19
b0 :
1(
#2240000
0(
#2244000
09
b1 :
1(
#2248000
0(
#2252000
b10 :
1(
#2256000
0(
#2260000
b11 :
1(
#2264000
0(
#2268000
b100 :
1(
#2272000
0(
#2276000
b101 :
1(
#2280000
0(
#2284000
b110 :
1(
#2288000
0(
#2292000
b111 :
1(
#2296000
0(
#2300000
b1000 :
1(
#2304000
0(
#2308000
b1001 :
1(
#2312000
0(
#2316000
b1010 :
1(
#2320000
0(
#2324000
b1011 :
1(
#2328000
0(
#2332000
b1100 :
1(
#2336000
0(
#2340000
b1101 :
1(
#2344000
0(
#2348000
b1110 :
1(
#2352000
0(
#2356000
b1111 :
1(
#2360000
0(
#2364000
b10000 :
1(
#2368000
0(
#2372000
b10001 :
1(
#2376000
0(
#2380000
b10010 :
1(
#2384000
0(
#2388000
b10011 :
1(
#2392000
0(
#2396000
19
b0 :
1(
#2400000
0(
#2404000
09
b1 :
1(
#2408000
0(
#2412000
b10 :
1(
#2416000
0(
#2420000
b11 :
1(
#2424000
0(
#2428000
b100 :
1(
#2432000
0(
#2436000
b101 :
1(
#2440000
0(
#2444000
b110 :
1(
#2448000
0(
#2452000
b111 :
1(
#2456000
0(
#2460000
b1000 :
1(
#2464000
0(
#2468000
b1001 :
1(
#2472000
0(
#2476000
b1010 :
1(
#2480000
0(
#2484000
b1011 :
1(
#2488000
0(
#2492000
b1100 :
1(
#2496000
0(
#2500000
b1101 :
1(
#2504000
0(
#2508000
b1110 :
1(
#2512000
0(
#2516000
b1111 :
1(
#2520000
0(
#2524000
b10000 :
1(
#2528000
0(
#2532000
b10001 :
1(
#2536000
0(
#2540000
b10010 :
1(
#2544000
0(
#2548000
b10011 :
1(
#2552000
0(
#2556000
19
b0 :
1(
#2560000
0(
#2564000
09
b1 :
1(
#2568000
0(
#2572000
b10 :
1(
#2576000
0(
#2580000
b11 :
1(
#2584000
0(
#2588000
b100 :
1(
#2592000
0(
#2596000
b101 :
1(
#2600000
0(
#2604000
b110 :
1(
#2608000
0(
#2612000
b111 :
1(
#2616000
0(
#2620000
b1000 :
1(
#2624000
0(
#2628000
b1001 :
1(
#2632000
0(
#2636000
b1010 :
1(
#2640000
0(
#2644000
b1011 :
1(
#2648000
0(
#2652000
b1100 :
1(
#2656000
0(
#2660000
b1101 :
1(
#2664000
0(
#2668000
b1110 :
1(
#2672000
0(
#2676000
b1111 :
1(
#2680000
0(
#2684000
b10000 :
1(
#2688000
0(
#2692000
b10001 :
1(
#2696000
0(
#2700000
b10010 :
1(
#2704000
0(
#2708000
b10011 :
1(
#2712000
0(
#2716000
19
b0 :
b10 &
b10 *
b0 D
b1 C
b11 '
b11 ,
1(
#2720000
0(
#2724000
b10 7
09
b1 :
1(
#2728000
0(
#2732000
b10 :
b10 8
1(
#2736000
0(
#2740000
b1000 $
b1000 +
b1000 -
b1000 B
b0 7
b11 4
b11 <
b11 :
b0 &
b0 *
1(
#2744000
0(
#2748000
b100 :
b0 8
1(
#2752000
0(
#2756000
b10 7
b101 :
b10 &
b10 *
b1 D
1(
#2760000
0(
#2764000
b110 :
b10 8
1(
#2768000
0(
#2772000
b111 :
1(
#2776000
0(
#2780000
b1000 :
b0 &
b0 *
1(
#2784000
0(
#2788000
b0 7
b1001 :
1(
#2792000
0(
#2796000
b1010 :
b0 8
b10 &
b10 *
b10 D
1(
#2800000
0(
#2804000
b10 7
b1011 :
1(
#2808000
0(
#2812000
b1100 :
b10 8
1(
#2816000
0(
#2820000
b0 7
b1101 :
b0 &
b0 *
1(
#2824000
0(
#2828000
b1110 :
b0 8
1(
#2832000
0(
#2836000
b10 7
b1111 :
b10 &
b10 *
b11 D
1(
#2840000
0(
#2844000
b10000 :
b10 8
1(
#2848000
0(
#2852000
b10001 :
1(
#2856000
0(
#2860000
b10010 :
b0 &
b0 *
1(
#2864000
0(
#2868000
b0 7
b10011 :
1(
#2872000
0(
#2876000
19
b0 :
b0 8
b10 &
b10 *
b100 D
1(
#2880000
0(
#2884000
b10 7
09
b1 :
1(
#2888000
0(
#2892000
b10 :
b10 8
1(
#2896000
0(
#2900000
b11 :
1(
#2904000
0(
#2908000
b100 :
1(
#2912000
0(
#2916000
b101 :
1(
#2920000
0(
#2924000
b110 :
1(
#2928000
0(
#2932000
b111 :
1(
#2936000
0(
#2940000
b1000 :
1(
#2944000
0(
#2948000
b1001 :
1(
#2952000
0(
#2956000
b1010 :
1(
#2960000
0(
#2964000
b1011 :
1(
#2968000
0(
#2972000
b1100 :
1(
#2976000
0(
#2980000
b1101 :
1(
#2984000
0(
#2988000
b1110 :
1(
#2992000
0(
#2996000
b1111 :
1(
#3000000
0(
#3004000
b10000 :
1(
#3008000
0(
#3012000
b10001 :
1(
#3016000
0(
#3020000
b10010 :
1(
#3024000
0(
#3028000
b10011 :
1(
#3032000
0(
#3036000
19
b0 :
1(
#3040000
0(
#3044000
09
b1 :
1(
#3048000
0(
#3052000
b10 :
1(
#3056000
0(
#3060000
b11 :
1(
#3064000
0(
#3068000
b100 :
1(
#3072000
0(
#3076000
b101 :
1(
#3080000
0(
#3084000
b110 :
1(
#3088000
0(
#3092000
b111 :
1(
#3096000
0(
#3100000
b1000 :
1(
#3104000
0(
#3108000
b1001 :
1(
#3112000
0(
#3116000
b1010 :
1(
#3120000
0(
#3124000
b1011 :
1(
#3128000
0(
#3132000
b1100 :
1(
#3136000
0(
#3140000
b1101 :
1(
#3144000
0(
#3148000
b1110 :
1(
#3152000
0(
#3156000
b1111 :
1(
#3160000
0(
#3164000
b10000 :
1(
#3168000
0(
#3172000
b10001 :
1(
#3176000
0(
#3180000
b10010 :
1(
#3184000
0(
#3188000
b10011 :
1(
#3192000
0(
#3196000
19
b0 :
1(
#3200000
0(
#3204000
09
b1 :
1(
#3208000
0(
#3212000
b10 :
1(
#3216000
0(
#3220000
b11 :
1(
#3224000
0(
#3228000
b100 :
1(
#3232000
0(
#3236000
b101 :
1(
#3240000
0(
#3244000
b110 :
1(
#3248000
0(
#3252000
b111 :
1(
#3256000
0(
#3260000
b1000 :
1(
#3264000
0(
#3268000
b1001 :
1(
#3272000
0(
#3276000
b1010 :
1(
#3280000
0(
#3284000
b1011 :
1(
#3288000
0(
#3292000
b1100 :
1(
#3296000
0(
#3300000
b1101 :
1(
#3304000
0(
#3308000
b1110 :
1(
#3312000
0(
#3316000
b1111 :
1(
#3320000
0(
#3324000
b10000 :
1(
#3328000
0(
#3332000
b10001 :
1(
#3336000
0(
#3340000
b10010 :
1(
#3344000
0(
